superofficesdk/__init__.py
superofficesdk/login.py
superofficesdk/partner.wsdl
superofficesdk/rest.py
superoffice_python_sdk-0.2.8.dist-info/METADATA
superoffice_python_sdk-0.2.8.dist-info/WHEEL
superoffice_python_sdk-0.2.8.dist-info/top_level.txt
superoffice_python_sdk-0.2.8.dist-info/RECORD
