Metadata-Version: 2.1
Name: superoffice-python-sdk
Version: 0.2.8
Summary: SuperOffice Python SDK
Home-page: UNKNOWN
Author: Ignotas Petrulis
Author-email: ignotas.petrulis@gmail.com
License: UNKNOWN
Platform: UNKNOWN
Requires-Dist: requests
Requires-Dist: suds-jurko
